plover_python_dictionary.py
plover_python_dictionary-1.2.1.dist-info/METADATA
plover_python_dictionary-1.2.1.dist-info/WHEEL
plover_python_dictionary-1.2.1.dist-info/entry_points.txt
plover_python_dictionary-1.2.1.dist-info/top_level.txt
plover_python_dictionary-1.2.1.dist-info/zip-safe
plover_python_dictionary-1.2.1.dist-info/RECORD
