Metadata-Version: 2.4
Name: plover-python-dictionary
Version: 1.2.1
Summary: Python dictionaries support for Plover
Home-page: https://github.com/benoit-pierre/plover_python_dictionary
Author: Benoit Pierre
Author-email: benoit.pierre@gmail.com
License: GNU General Public License v2 or later (GPLv2+)
Keywords: plover plover_plugin
Classifier: Development Status :: 4 - Beta
Classifier: Environment :: Plugins
Classifier: Intended Audience :: End Users/Desktop
Classifier: License :: OSI Approved :: GNU General Public License v2 or later (GPLv2+)
Classifier: Operating System :: OS Independent
Classifier: Programming Language :: Python :: 3
Classifier: Programming Language :: Python :: 3.6
Classifier: Programming Language :: Python :: 3.7
Classifier: Programming Language :: Python :: 3.8
Classifier: Programming Language :: Python :: 3.9
Requires-Python: >=3.6
Requires-Dist: plover>=4.0.0.dev5
Provides-Extra: test
Requires-Dist: plover>=4.0.0.dev10; extra == "test"
Requires-Dist: pytest>=3.0.1; extra == "test"
